{
  "provisioners": [
    {
      "type": "shell",
      "override": {
        "virtualbox-iso": {
          "scripts": ["scripts/provision.sh"]
        }
      }
    }
  ],
  "post-processors": [
    {
      "type": "vagrant",
      "override": {
        "virtualbox": {
          "output": "android-x86_64-virtualbox.box"
        }
      }
    }
  ],
  "builders": [
    {
      "type": "virtualbox-iso",
      "boot_command": [
        "<down><down><down><enter><enter><wait5>",
	"<enter><enter><wait5><right><enter><enter><enter><enter><left><enter>yes<enter><wait5>",
	"<left><left><left><left><enter><wait5>",
	"<enter><wait5><down><enter><wait5><left><enter><wait10><wait5>",
	"<left><enter><wait5><enter><wait5><enter><wait10><wait10><wait10><wait10><wait10><wait10>",
	"<down><enter><wait5><down><enter><wait10><enter><wait5>",
	"find / -name '*.apk' | grep setup -i | xargs rm<enter><wait5>",
	"mount -o rw,remount /<enter><wait5>",
	"cat /system/usr/keylayout/Generic.kl | awk '{ if ($2 == \"59\") {$3 = \"   MENU\"}; print }' > remap.kl<enter><wait5>",
	"mv remap.kl /system/usr/keylayout/Generic.kl<enter><wait5>",
	"exit<enter><wait5>exit<enter><wait5>",
	"<wait10><wait10><wait10><wait10><wait10><wait10><wait10>",
	"<down><wait5><enter><wait5><down><wait5><enter><wait5><down><wait5><enter><wait5>",
	"<right><wait><right><wait><right><wait><right><wait><down><wait><left><wait><left><wait><enter><wait5>",
	"<down><wait5><right><wait5><right><wait5><right><wait5><right><wait5><right><wait5><right><wait5><right><wait5><enter><wait5>",
	"<down><wait5><down><wait5><down><wait5><down><wait5><down><wait5><down><wait5><right><wait5><enter><wait5>",
	"<down><wait5><down><wait5><down><wait5><down><wait5><down><wait5><down><wait5><enter><wait5>",
	"<right><wait5><enter><wait5>",
	"<esc><wait5><esc><wait5><enter><wait5>",
	"<down><wait5><down><wait5><down><wait5><enter><wait5>",
	"<down><wait5><enter><wait5>",
	"<down><wait5><enter><wait5>",
	"<tab><wait5><tab><wait5><tab><wait5><tab><wait5><enter><wait5>",
	"<esc><wait5><esc><wait5><esc><wait5><esc><wait5><esc>",
	"<right><wait><right><wait><right><wait><right><wait><down><wait><left><wait><left><wait><left><wait><enter><wait5>",
	"<up><wait5><up><wait><up><down><wait><down><wait><up><wait5>https://github.com/meefik/linuxdeploy/releases/download/2.0.1/linuxdeploy-2.0.1-218.apk<enter><wait10>",
	"<esc><wait5><esc><wait5><esc><wait5><esc><wait5><esc><wait5>",
	"<right><wait><right><wait><right><wait><right><wait><down><wait><left><wait><left><wait><enter><wait5>",
	"<right><wait5><right><wait5><right><wait5><right><wait5><right><wait5><right><wait5><enter><wait10>",
	"<enter><wait10><right><wait5><enter><wait10>",
	"<wait10><wait10><wait10><wait10><wait10>",
	"<right><wait5><left><wait5><enter><wait10>",
	"<esc><wait5><esc><wait5><esc><wait5><esc><wait5><esc>",
	"<enter><wait5><right><wait5><right><wait5><down><enter><wait10>",
	"<esc><wait5><right><wait5><right><wait5><right><wait5><right><wait5><right><wait5><right><wait5><right><wait5><enter><wait5>",
	"su<enter><wait5><wait5><down><wait5><down><wait5><enter><wait5><right><enter><wait5>",
	"cd /data/data/ru.meefik.linuxdeploy/<enter><wait5>",
	"echo -e 'CHROOT_DIR=\"/data/local/mnt\"\\nPROFILE=\"linux\"\\n' > env/cli.conf<enter><wait5>",
	"echo -e 'ARCH=\"i686\"\\nDESKTOP=\"lxcde\"\\nDISK_SIZE=\"0\"\\nDISTRIB=\"archlinux\"\\nDNS=\"\"\\nFB_ARGS=\"-dpi 100 -sharevts vt0\"\\nFB_DEV=\"/dev/graphics/fb0\"\\nFB_DISPLAY=\"0\"\\nFB_FREEZE=\"none\"\\nFB_INPUT=\"/dev/input/event0\"\\nFB_REFRESH=\"true\"\\nFS_TYPE=\"auto\"\\nGRAPHICS=\"vnc\"\\nINCLUDE=\"bootstrap extra/ssh\"\\nINIT=\"run-parts\"\\nINIT_ASYNC=\"true\"\\nINIT_LEVEL=\"3\"\\nINIT_PATH=\"/usr/rc.local\"\\nINIT_USER=\"root\"\\nLOCALE=\"POSIX\"\\nMETHOD=\"chroot\"\\nMOUNTS=\"\"\\nPRIVILEGED_USERS=\"root\"\\nSOURCE_PATH=\"http://mirrors.kernel.org/archlinux/\"\\nSSH_ARGS=\"\"\\nSSH_PORT=\"22\"\\nSUITE=\"latest\"\\nTARGET_PATH=\"${EXTERNAL_STORAGE}/linux.img\"\\nTARGET_TYPE=\"file\"\\nUSER_NAME=\"android\"\\nUSER_PASSWORD=\"android\"\\nVNC_ARGS=\"\"\\nVNC_DEPTH=\"16\"\nVNC_DISPLAY=\"0\"\\nVNC_DPI=\"75\"\\nVNC_HEIGHT=\"720\"\\nVNC_WIDTH=\"1024\"\\nX11_DISPLAY=\"0\"\\nX11_HOST=\"127.0.0.1\"\\nX11_SDL=\"false\"\\nX11_SDL_DELAY=\"15\"\\n' > env/config/linux.conf<enter><wait5>",
	"exit<enter><wait5>",
	"exit<enter><wait10>",
	"<down><wait5><right><wait5><enter><wait5>",
	"<f1><wait5><enter><wait5><right><wait5><enter><wait5>",
	"<up><wait5><enter><wait5><right><wait5><enter><wait5>",
	"<wait10><wait10><wait10><wait10><wait10>",
	"<wait10><wait10><wait10><wait10><wait10>",
	"<wait10><wait10><wait10><wait10><wait10>",
	"<wait10><wait10><wait10><wait10><wait10>",
	"<wait10><wait10><wait10><wait10><wait10>",
	"<esc><wait5><right><wait5><right><wait5><right><wait5><right><wait5><right><wait5><right><wait5><right><wait5><enter><wait5>",
	"su<enter><wait5>",
	"cd /data/data/ru.meefik.linuxdeploy/<enter><wait5>",
	"sh env/cli.sh start<enter><wait5>",
	"mount -o rw,remount /<enter><wait5>",
	"sed -i '1s/^/\\(sleep 10; cd \\/data\\/data\\/ru.meefik.linuxdeploy\\/bin\\/; .\\/linuxdeploy mount; .\\/linuxdeploy start\\)\\&\\n/' /etc/init.sh<enter><wait5>"
      ],
      "boot_wait": "10s",
      "disk_size": 40960,
      "guest_os_type": "Linux26_64",
      "http_directory": "http",
      "iso_url": "http://onet.dl.osdn.jp/android-x86/65890/android-x86_64-6.0-r1.iso",
      "iso_checksum": "4e65b707acb97e62a9835b4688cac242a83136e7",
      "iso_checksum_type": "sha1",
      "ssh_username": "android",
      "ssh_password": "android",
      "ssh_port": 22,
      "vboxmanage": [
        [
	  "modifyvm",
	  "{{.Name}}",
	  "--memory",
	  "4096"
        ]
      ]
    }
  ]
}
